pdf2text/__init__.py
pdf2text/config.py
pdf2text/main.py
pdf2text/analyzers/__init__.py
pdf2text/analyzers/memory_estimator.py
pdf2text/analyzers/pdf_analyzer.py
pdf2text/core/__init__.py
pdf2text/core/agent.py
pdf2text/core/file_manager.py
pdf2text/core/memory_manager.py
pdf2text/extractors/__init__.py
pdf2text/extractors/hybrid_extractors.py
pdf2text/extractors/ocr_extractors.py
pdf2text/extractors/text_extractors.py
pdf2text/utils/__init__.py
pdf2text/utils/logger.py
pdf2text_agent-0.1.1.dist-info/METADATA
pdf2text_agent-0.1.1.dist-info/WHEEL
pdf2text_agent-0.1.1.dist-info/entry_points.txt
pdf2text_agent-0.1.1.dist-info/top_level.txt
pdf2text_agent-0.1.1.dist-info/RECORD
