Metadata-Version: 2.4
Name: pdf2text-agent
Version: 0.1.1
Summary: A Python tool to extract text from various PDF types using direct extraction and OCR, with built-in memory management.
Author-email: PDF2Text Contributor <contributor@example.com>
License-Expression: MIT
Project-URL: Homepage, https://github.com/example/pdf2text-agent
Project-URL: Repository, https://github.com/example/pdf2text-agent
Classifier: Development Status :: 4 - Beta
Classifier: Intended Audience :: Developers
Classifier: Intended Audience :: End Users/Desktop
Classifier: Programming Language :: Python :: 3
Classifier: Programming Language :: Python :: 3.9
Classifier: Programming Language :: Python :: 3.10
Classifier: Programming Language :: Python :: 3.11
Classifier: Programming Language :: Python :: 3.12
Classifier: Topic :: Text Processing :: General
Classifier: Topic :: Utilities
Classifier: Operating System :: OS Independent
Requires-Python: >=3.9
Requires-Dist: psutil>=5.0.0
Requires-Dist: PyMuPDF>=1.20.0
Requires-Dist: pytesseract>=0.3.0
Requires-Dist: pdf2image>=1.16.0
Requires-Dist: Pillow>=9.0.0
Requires-Dist: numpy>=1.20.0
Requires-Dist: pdfplumber>=0.10.0
